{
  "Black Tech": {
    "7002106": {
      "points": 61
    },
    "1216533": {
      "points": 58
    }
  },
  "The Pharaohs": {
    "275539": {
      "points": 57
    },
    "1545049": {
      "points": 55
    }
  },
  "Smokers": {
    "1679155": {
      "points": 60
    },
    "2208753": {
      "points": 72
    }
  },
  "Falcons": {
    "2134302": {
      "points": 78
    },
    "8656672": {
      "points": 87
    }
  },
  "Boys": {
    "8703485": {
      "points": 66
    },
    "5857198": {
      "points": 56
    }
  }
}